source/__init__.py
source/app.py
cfn_cur-0.1.4.dist-info/METADATA
cfn_cur-0.1.4.dist-info/WHEEL
cfn_cur-0.1.4.dist-info/entry_points.txt
cfn_cur-0.1.4.dist-info/licenses/LICENSE
cfn_cur-0.1.4.dist-info/RECORD
