Metadata-Version: 2.4
Name: cfn-cur
Version: 0.1.4
Summary: A tool to generate CLI Command to continue update rollback of CloudFormation stacks
Project-URL: Homepage, https://github.com/mrlikl/continue-update-rollback
Author-email: S Murali Krishnan <mrlikrsh@gmail.com>
License-File: LICENSE
Keywords: aws,cloudformation,continue,failed,rollback,update
Classifier: Operating System :: OS Independent
Classifier: Programming Language :: Python :: 3
Classifier: Topic :: Utilities
Requires-Python: >=3.9
Requires-Dist: botocore
Requires-Dist: typer
